moon_cloud_coder/__init__.py
moon_cloud_coder/__main__.py
moon_cloud_coder/main.py
moon_cloud_coder/ai/__init__.py
moon_cloud_coder/ai/client.py
moon_cloud_coder/auth/auth_handler.py
moon_cloud_coder/auth/oauth_progress.py
moon_cloud_coder/auth/qwen_oauth.py
moon_cloud_coder/cli/__init__.py
moon_cloud_coder/cli/app.py
moon_cloud_coder/utils/__init__.py
moon_cloud_coder/utils/config.py
moon_cloud_coder/utils/logger.py
moon_cloud_coder-0.0.1.dist-info/licenses/LICENSE
moon_cloud_coder-0.0.1.dist-info/METADATA
moon_cloud_coder-0.0.1.dist-info/WHEEL
moon_cloud_coder-0.0.1.dist-info/entry_points.txt
moon_cloud_coder-0.0.1.dist-info/top_level.txt
moon_cloud_coder-0.0.1.dist-info/RECORD
