Metadata-Version: 2.4
Name: moon-cloud-coder
Version: 0.0.1
Summary: AI-powered command line tool for developers using Qwen models
Author: Moon Cloud Coder Team
License: MIT
Project-URL: Homepage, https://github.com/your-username/moon-cloud-coder
Project-URL: Repository, https://github.com/your-username/moon-cloud-coder
Project-URL: Documentation, https://github.com/your-username/moon-cloud-coder/blob/main/README.md
Project-URL: Issues, https://github.com/your-username/moon-cloud-coder/issues
Classifier: Development Status :: 3 - Alpha
Classifier: Intended Audience :: Developers
Classifier: License :: OSI Approved :: MIT License
Classifier: Programming Language :: Python :: 3
Classifier: Programming Language :: Python :: 3.8
Classifier: Programming Language :: Python :: 3.9
Classifier: Programming Language :: Python :: 3.10
Classifier: Programming Language :: Python :: 3.11
Classifier: Programming Language :: Python :: 3.12
License-File: LICENSE
Requires-Dist: dashscope==1.22.1
Requires-Dist: typer>=0.9.0
Requires-Dist: rich>=13.0.0
Requires-Dist: openai>=1.0.0
Provides-Extra: dev
Requires-Dist: pytest>=6.0; extra == "dev"
Requires-Dist: pytest-cov; extra == "dev"
Requires-Dist: black; extra == "dev"
Requires-Dist: flake8; extra == "dev"
Requires-Dist: mypy; extra == "dev"
Dynamic: license-file
